{"cameraMode":{"drawMode":0,"name":"Shaded","section":"Shading Mode"},"sceneLighting":false,"audioPlay":false,"sceneViewState":{"m_AlwaysRefresh":false,"showFog":true,"showSkybox":false,"showFlares":true,"showImageEffects":true,"showParticleSystems":true,"showVisualEffectGraphs":true,"m_FxEnabled":true},"in2DMode":false,"pivot":{"x":0.0831717699766159,"y":0.1631869226694107,"z":0.11443537473678589},"rotation":{"x":-0.30182310938835146,"y":-0.5071007609367371,"z":0.19545994699001313,"w":-0.7833388447761536},"size":0.4514632225036621,"orthographic":false}